dj_jsonfield-1.0.0.dist-info/metadata.json
dj_jsonfield-1.0.0.dist-info/DESCRIPTION.rst
dj_jsonfield-1.0.0.dist-info/METADATA
dj_jsonfield-1.0.0.dist-info/WHEEL
dj_jsonfield-1.0.0.dist-info/top_level.txt
dj_jsonfield-1.0.0.dist-info/RECORD
dj_jsonfield/utils.py
dj_jsonfield/models.py
dj_jsonfield/__init__.py
dj_jsonfield/forms.py
dj_jsonfield/fields.py
dj_jsonfield/VERSION
dj_jsonfield/widgets.py
dj_jsonfield/templatetags/jsonify.py
dj_jsonfield/templatetags/__init__.py
dj_jsonfield/tests/__init__.py
dj_jsonfield/tests/test_fields.py
dj_jsonfield/tests/test_forms.py
dj_jsonfield/tests/jsonfield_test_app/models.py
dj_jsonfield/tests/jsonfield_test_app/__init__.py
dj_jsonfield/tests/jsonfield_test_app/forms.py
