Metadata-Version: 2.0
Name: dj-jsonfield
Version: 1.0.0
Summary: JSONField for django models
Home-page: https://github.com/ratson/dj-jsonfield/
Author: Ratson
Author-email: contact@ratson.name
License: UNKNOWN
Platform: UNKNOWN
Classifier: Programming Language :: Python
Classifier: Programming Language :: Python :: 3
Classifier: License :: OSI Approved :: BSD License
Classifier: Operating System :: OS Independent
Classifier: Framework :: Django
